good_first_issues/__init__.py
good_first_issues/main.py
good_first_issues/commands/__init__.py
good_first_issues/commands/config.py
good_first_issues/commands/rate_limit.py
good_first_issues/commands/search.py
good_first_issues/commands/version.py
good_first_issues/graphql/__init__.py
good_first_issues/graphql/queries.py
good_first_issues/graphql/services.py
good_first_issues/utils/__init__.py
good_first_issues-2.1.5.dist-info/LICENCE
good_first_issues-2.1.5.dist-info/METADATA
good_first_issues-2.1.5.dist-info/WHEEL
good_first_issues-2.1.5.dist-info/entry_points.txt
good_first_issues-2.1.5.dist-info/top_level.txt
good_first_issues-2.1.5.dist-info/RECORD
