Metadata-Version: 2.1
Name: good-first-issues
Version: 2.1.5
Summary: Find good first issues right from your CLI!
Home-page: https://github.com/yankeexe/good-first-issues
Author: Yankee Maharjan
License: MIT
Project-URL: Bug Reports, https://github.com/yankeexe/good-first-issues/issues
Project-URL: Source, https://github.com/yankeexe/good-first-issues
Classifier: Intended Audience :: Developers
Classifier: Programming Language :: Python :: 3.9
Classifier: Programming Language :: Python :: 3.10
Classifier: Programming Language :: Python :: 3.11
Classifier: Operating System :: OS Independent
Classifier: Development Status :: 4 - Beta
Classifier: License :: OSI Approved :: MIT License
Requires-Python: >=3.9
License-File: LICENCE
Requires-Dist: click ==8.1.7
Requires-Dist: halo ==0.0.31
Requires-Dist: requests ==2.32.3
Requires-Dist: rich <=13.7.1
Requires-Dist: tabulate ==0.9.0
Provides-Extra: dev
Requires-Dist: mypy ; extra == 'dev'
Requires-Dist: pre-commit ; extra == 'dev'
Requires-Dist: pytest ==8.2.2 ; extra == 'dev'
Requires-Dist: ruff ==0.9.4 ; extra == 'dev'
